00_src/adder_1b.sv
module adder_1b
(
        input   logic   a, b, cin,
        output  logic   sum, cout
);

assign sum = a ^ b ^ cin;
assign cout = (a & b) | (cin & (a ^ b));

endmodule:adder_1b

00_src/adder_nb.sv
module adder_nb
#(parameter WIDTH = 32)
(
    input   logic   [WIDTH-1:0] a, b,
    input   logic               cin,
    output  logic   [WIDTH-1:0] sum,
    output  logic               cout
);

logic [31:0] carry;

adder_1b a1  (.sum(sum[0]),  .a(a[0]),  .b(b[0]^cin),  .cin(cin),       .cout(carry[0]));
adder_1b a2  (.sum(sum[1]),  .a(a[1]),  .b(b[1]^cin),  .cin(carry[0]),  .cout(carry[1]));
adder_1b a3  (.sum(sum[2]),  .a(a[2]),  .b(b[2]^cin),  .cin(carry[1]),  .cout(carry[2]));
adder_1b a4  (.sum(sum[3]),  .a(a[3]),  .b(b[3]^cin),  .cin(carry[2]),  .cout(carry[3]));
adder_1b a5  (.sum(sum[4]),  .a(a[4]),  .b(b[4]^cin),  .cin(carry[3]),  .cout(carry[4]));
adder_1b a6  (.sum(sum[5]),  .a(a[5]),  .b(b[5]^cin),  .cin(carry[4]),  .cout(carry[5]));
adder_1b a7  (.sum(sum[6]),  .a(a[6]),  .b(b[6]^cin),  .cin(carry[5]),  .cout(carry[6]));
adder_1b a8  (.sum(sum[7]),  .a(a[7]),  .b(b[7]^cin),  .cin(carry[6]),  .cout(carry[7]));
adder_1b a9  (.sum(sum[8]),  .a(a[8]),  .b(b[8]^cin),  .cin(carry[7]),  .cout(carry[8]));
adder_1b a10 (.sum(sum[9]),  .a(a[9]),  .b(b[9]^cin),  .cin(carry[8]),  .cout(carry[9]));
adder_1b a11 (.sum(sum[10]), .a(a[10]), .b(b[10]^cin), .cin(carry[9]),  .cout(carry[10]));
adder_1b a12 (.sum(sum[11]), .a(a[11]), .b(b[11]^cin), .cin(carry[10]), .cout(carry[11]));
adder_1b a13 (.sum(sum[12]), .a(a[12]), .b(b[12]^cin), .cin(carry[11]), .cout(carry[12]));
adder_1b a14 (.sum(sum[13]), .a(a[13]), .b(b[13]^cin), .cin(carry[12]), .cout(carry[13]));
adder_1b a15 (.sum(sum[14]), .a(a[14]), .b(b[14]^cin), .cin(carry[13]), .cout(carry[14]));
adder_1b a16 (.sum(sum[15]), .a(a[15]), .b(b[15]^cin), .cin(carry[14]), .cout(carry[15]));
adder_1b a17 (.sum(sum[16]), .a(a[16]), .b(b[16]^cin), .cin(carry[15]), .cout(carry[16]));
adder_1b a18 (.sum(sum[17]), .a(a[17]), .b(b[17]^cin), .cin(carry[16]), .cout(carry[17]));
adder_1b a19 (.sum(sum[18]), .a(a[18]), .b(b[18]^cin), .cin(carry[17]), .cout(carry[18]));
adder_1b a20 (.sum(sum[19]), .a(a[19]), .b(b[19]^cin), .cin(carry[18]), .cout(carry[19]));
adder_1b a21 (.sum(sum[20]), .a(a[20]), .b(b[20]^cin), .cin(carry[19]), .cout(carry[20]));
adder_1b a22 (.sum(sum[21]), .a(a[21]), .b(b[21]^cin), .cin(carry[20]), .cout(carry[21]));
adder_1b a23 (.sum(sum[22]), .a(a[22]), .b(b[22]^cin), .cin(carry[21]), .cout(carry[22]));
adder_1b a24 (.sum(sum[23]), .a(a[23]), .b(b[23]^cin), .cin(carry[22]), .cout(carry[23]));
adder_1b a25 (.sum(sum[24]), .a(a[24]), .b(b[24]^cin), .cin(carry[23]), .cout(carry[24]));
adder_1b a26 (.sum(sum[25]), .a(a[25]), .b(b[25]^cin), .cin(carry[24]), .cout(carry[25]));
adder_1b a27 (.sum(sum[26]), .a(a[26]), .b(b[26]^cin), .cin(carry[25]), .cout(carry[26]));
adder_1b a28 (.sum(sum[27]), .a(a[27]), .b(b[27]^cin), .cin(carry[26]), .cout(carry[27]));
adder_1b a29 (.sum(sum[28]), .a(a[28]), .b(b[28]^cin), .cin(carry[27]), .cout(carry[28]));
adder_1b a30 (.sum(sum[29]), .a(a[29]), .b(b[29]^cin), .cin(carry[28]), .cout(carry[29]));
adder_1b a31 (.sum(sum[30]), .a(a[30]), .b(b[30]^cin), .cin(carry[29]), .cout(carry[30]));
adder_1b a32 (.sum(sum[31]), .a(a[31]), .b(b[31]^cin), .cin(carry[30]), .cout(carry[31]));

xor (cout, carry[31], cin);

endmodule:adder_nb

00_src/imem.sv
`timescale 1ns/1ps

module imem
(
    input   logic   [31:0]  a,
    output  logic   [31:0]  rd
);

logic   [31:0]  RAM [63:0];

initial
    $readmemh("imem.txt", RAM);

assign rd = RAM[a[7:2]]; // word aligned - divide address by 4

endmodule: imem

00_src/flop_r.sv
module flop_r 
#(parameter WIDTH = 8)

(
    input   logic               clk, rst, en, clr,
    input   logic   [WIDTH-1:0] d,
    output  logic   [WIDTH-1:0] q
);

always_ff @(posedge clk, posedge rst)
    if      (rst)   q <= 0;
    else if (clr)   q <= 0;
    else if (en)    q <= d;

endmodule

00_src/mux_2.sv
module mux_2 
#(parameter WIDTH = 32)
(
    input   logic   [WIDTH-1:0] d0, d1,
    input   logic               s,
    output  logic   [WIDTH-1:0] y
);

assign y = s ? d1 : d0;

endmodule:mux_2

01_bench/F_stage_tb.sv
`timescale 1ns/1ps

module F_stage_tb;

// Signals
logic           clk, rst;        // System signals
logic           StallF;          // Control signal from Hazard Unit
logic           PCSrcE;          // Control signal from Controller
logic [31:0]    PCTargetE;       // Input bus from Execute stage
logic [31:0]    pcF0, pcF;      // Internal signals: Next PC, Current PC
logic [31:0]    PCPlus4F;       // Internal signal: PC + 4
logic [31:0]    InstrF;         // Output to Decode stage

// Clock generation
always begin
    clk = 1; #5;
    clk = 0; #5;
end

// DUT instantiation
mux_2 #(.WIDTH(32)) PCmux
(
    .d0     (PCPlus4F),
    .d1     (PCTargetE),
    .s      (PCSrcE),    
    .y      (pcF0)
);

flop_r #(.WIDTH(32)) Freg
(
    .clk    (clk),
    .rst    (rst),
    .en     (~StallF),
    .clr    (1'b0),
    .d      (pcF0),
    .q      (pcF)
);

imem imem
(
    .a      (pcF),
    .rd     (InstrF)
);

logic PCplus4cout;
adder_nb #(.WIDTH(32)) PCplus4
(
    .a      (pcF),
    .b      (32'd4),
    .cin    (1'b0),
    .cout   (PCplus4cout),
    .sum    (PCPlus4F)
);

// Test counters
int test_num = 0;
int pass_count = 0;
int fail_count = 0;

// Task for checking results
task run_test(
    input logic [31:0] exp_pcF0,      // Expected next PC (mux output)
    input logic [31:0] exp_pcF,       // Expected current PC (register output)
    input logic [31:0] exp_InstrF,    // Expected instruction
    input string test_name
);
    test_num++;
    #1; // Small delay for signal settling

    if ((pcF0 === exp_pcF0) && (pcF === exp_pcF) && (InstrF === exp_InstrF)) begin
        $display("%02d ✅PASSED %s", test_num, test_name);
        $display("        pcF0=%h pcF=%h InstrF=%h", pcF0, pcF, InstrF);
        pass_count++;
    end else begin
        $display("%02d ❌FAILED %s", test_num, test_name);
        $display("        Expected: pcF0=%h pcF=%h InstrF=%h", 
                exp_pcF0, exp_pcF, exp_InstrF);
        $display("        Actual:   pcF0=%h pcF=%h InstrF=%h", 
                pcF0, pcF, InstrF);
        fail_count++;
    end
endtask

initial begin
    $dumpfile("wave.vcd");
    $dumpvars(0, F_stage_tb);

    $display("\n===== Fetch Stage Tests =====");

    // // Test 0: Reset State
    // $display("\n----------- Reset Test -----------");
    // // Set inputs
    // rst = 1;
    // StallF = 0;
    // PCSrcE = 0;
    // PCTargetE = 32'h0;
    // #10;
    // // Check outputs
    // run_test(32'h00000004,    // pcF0 = PCPlus4F (PC + 4)
    //          32'h00000000,    // pcF = reset value
    //          32'h00500113,    // InstrF = first instruction in imem.txt
    //          "Reset state");
    // rst = 0;

    // // Test 1: Sequential Fetch
    // $display("\n----------- Sequential Fetch -----------");
    // // Set inputs
    // rst = 0;
    // StallF = 0;
    // PCSrcE = 0;
    // PCTargetE = 32'h0;
    // repeat(4) begin
    //     @(posedge clk);
    //     run_test(pcF + 8,                    // pcF0 = current PC + 8
    //              pcF + 4,                    // pcF = current PC + 4
    //              imem.RAM[(pcF + 4) >> 2],   // Next instruction in sequence
    //              "Sequential fetch");
    // end

    // // Test 2: Stall Test
    // $display("\n----------- Stall Test -----------");
    // // Set inputs
    // rst = 0;
    // StallF = 1;              // Enable stall
    // PCSrcE = 1;              // Try to take branch
    // PCTargetE = 32'h00000020;  // Branch target
    // @(posedge clk);
    // run_test(32'h00000020,                  // pcF0 = PCTargetE
    //          pcF,                           // pcF unchanged due to stall
    //          imem.RAM[pcF >> 2],            // InstrF unchanged
    //          "Stall active");

    // // Test 3: Branch/Jump Test
    // $display("\n----------- Branch/Jump Test -----------");
    // // Set inputs
    // rst = 0;
    // StallF = 0;              // Release stall
    // PCSrcE = 1;              // Keep branch signal
    // PCTargetE = 32'h00000020;  // Same branch target
    // @(posedge clk);
    // run_test(32'h00000020,                  // pcF0 = PCTargetE (due to PCSrcE=1)
    //          32'h00000020,                  // pcF = branch target
    //          imem.RAM[32'h20 >> 2],         // InstrF at branch target
    //          "Branch taken");

    // // Test 4: Edge Cases
    // $display("\n----------- Edge Cases -----------");
    
    // // Test 4.1: Maximum PC
    // // Set inputs
    // rst = 0;
    // StallF = 0;
    // PCSrcE = 1;
    // PCTargetE = 32'hFFFFFFFC;  // Max aligned address
    // @(posedge clk);
    // run_test(32'hFFFFFFFC,                  // pcF0 wraps to 0
    //          32'hFFFFFFFC,                  // pcF = max aligned address
    //          imem.RAM[32'hFFFFFFFC >> 2],   // InstrF at max address
    //          "Maximum PC value");

    // // Test 4.2: Quick control change
    // // Set inputs
    // rst = 0;
    // StallF = 0;
    // PCSrcE = 1;
    // PCTargetE = 32'h00000010;
    // #1 PCSrcE = 0;          // Change PCSrcE within same cycle
    // @(posedge clk);
    // run_test(32'h00000004,                  // pcF0 = PCPlus4F
    //          32'h00000000,                  // pcF = current PC
    //          imem.RAM[0],                   // InstrF at address 0
    //          "Quick control change");

    // // Test 4.3: Reset during operation
    // // Set inputs
    // rst = 1;                // Assert reset
    // StallF = 0;
    // PCSrcE = 0;
    // PCTargetE = 32'h0;
    // @(posedge clk);
    // run_test(32'h00000004,                  // pcF0 = PC + 4
    //          32'h00000000,                  // pcF = reset value
    //          32'h00500113,                  // First instruction
    //          "Reset during execution");

    // Test 0: Reset Cases
    $display("\n----------- Reset Tests -----------");
    // Case 0.1: Initial reset
    rst = 1; StallF = 0; PCSrcE = 0; PCTargetE = 32'h0;
    #10;
    run_test(32'h00000004, 32'h00000000, 32'h00500113, "Initial reset");
    
    // Case 0.2: Reset with branch pending
    rst = 1; StallF = 0; PCSrcE = 1; PCTargetE = 32'h00000020;
    @(posedge clk);
    run_test(32'h00000020, 32'h00000000, 32'h00500113, "Reset overrides branch");
    
    // Case 0.3: Reset with stall active
    rst = 1; StallF = 1; PCSrcE = 0; PCTargetE = 32'h0;
    @(posedge clk);
    run_test(32'h00000004, 32'h00000000, 32'h00500113, "Reset overrides stall");
    rst = 0;

    // Test 1: Sequential Fetch Cases
    $display("\n----------- Sequential Fetch Tests -----------");
    // Case 1.1: Basic sequential fetch
    rst = 0; StallF = 0; PCSrcE = 0; PCTargetE = 32'h0;
    repeat(4) begin
        @(posedge clk);
        run_test(pcF + 8, pcF + 4, imem.RAM[(pcF + 4) >> 2], "Basic sequential");
    end
    
    // Case 1.2: Sequential after branch cancelled
    PCSrcE = 1; #1; PCSrcE = 0;
    @(posedge clk);
    run_test(pcF + 8, pcF + 4, imem.RAM[(pcF + 4) >> 2], "Sequential after branch cancel");

    // Test 2: Stall Cases
    $display("\n----------- Stall Tests -----------");
    // Case 2.1: Single cycle stall
    rst = 0; StallF = 1; PCSrcE = 0; PCTargetE = 32'h0;
    @(posedge clk);
    run_test(pcF + 4, pcF, imem.RAM[pcF >> 2], "Single cycle stall");
    
    // Case 2.2: Multi-cycle stall
    repeat(3) begin
        @(posedge clk);
        run_test(pcF + 4, pcF, imem.RAM[pcF >> 2], "Multi-cycle stall");
    end
    
    // Case 2.3: Stall with branch attempt
    PCSrcE = 1; PCTargetE = 32'h00000020;
    @(posedge clk);
    run_test(32'h00000020, pcF, imem.RAM[pcF >> 2], "Stall ignores branch");
    
    // Case 2.4: Release stall
    StallF = 0;
    @(posedge clk);
    run_test(32'h00000020, 32'h00000020, imem.RAM[32'h20 >> 2], "Stall release");

    // Test 3: Branch/Jump Cases
    $display("\n----------- Branch/Jump Tests -----------");
    // Case 3.1: Basic branch
    rst = 0; StallF = 0; PCSrcE = 1; PCTargetE = 32'h00000008;
    @(posedge clk);
    run_test(32'h00000008, 32'h00000008, imem.RAM[32'h8 >> 2], "Basic branch");
    
    // Case 3.2: Back-to-back branches
    PCTargetE = 32'h00000010;
    @(posedge clk);
    run_test(32'h00000010, 32'h00000010, imem.RAM[32'h10 >> 2], "Back-to-back branch");
    
    // Case 3.3: Branch to current PC
    PCTargetE = pcF;
    @(posedge clk);
    run_test(pcF, pcF, imem.RAM[pcF >> 2], "Branch to current PC");

    // Test 4: Edge Cases
    $display("\n----------- Edge Cases -----------");
    // Case 4.1: Maximum PC
    rst = 0; StallF = 0; PCSrcE = 1; PCTargetE = 32'hFFFFFFFC;
    @(posedge clk);
    run_test(32'hFFFFFFFC, 32'hFFFFFFFC, imem.RAM[32'hFFFFFFFC >> 2], "Maximum PC");
    
    // Case 4.2: PC wrap-around
    rst = 0; StallF = 0; PCSrcE = 0;
    @(posedge clk);
    run_test(32'h00000004, 32'h00000000, imem.RAM[0], "PC wrap-around");
    
    // Case 4.3: Quick control changes
    rst = 0; StallF = 0;
    PCSrcE = 1; PCTargetE = 32'h00000020; #1;
    PCSrcE = 0; #1;
    StallF = 1; #1;
    rst = 1;
    @(posedge clk);
    run_test(32'h00000004, 32'h00000000, 32'h00500113, "Multiple control changes");

    // Display test statistics
    $display("\n===== Test Statistics =====");
    $display("Total Tests:  %0d", test_num);
    $display("✅ Tests Passed: %0d (%0.1f%%)", pass_count, (pass_count * 100.0) / test_num);
    $display("❌ Tests Failed: %0d (%0.1f%%)", fail_count, (fail_count * 100.0) / test_num);
    $display("===========================\n");

    $finish;
end

endmodule

10_sim/verilator/wave.vcd
$version Generated by VerilatedVcd $end
$timescale 1ps $end
 $scope module $rootio $end
 $upscope $end
 $scope module F_stage_tb $end
  $var wire 1 +! clk $end
  $var wire 1 # rst $end
  $var wire 1 $ StallF $end
  $var wire 1 % PCSrcE $end
  $var wire 32 & PCTargetE [31:0] $end
  $var wire 32 ,! pcF0 [31:0] $end
  $var wire 32 + pcF [31:0] $end
  $var wire 32 , PCPlus4F [31:0] $end
  $var wire 32 -! InstrF [31:0] $end
  $var wire 1 - PCplus4cout $end
  $var wire 32 ' test_num [31:0] $end
  $var wire 32 ( pass_count [31:0] $end
  $var wire 32 ) fail_count [31:0] $end
  $scope module Freg $end
   $var wire 32 .! WIDTH [31:0] $end
   $var wire 1 +! clk $end
   $var wire 1 # rst $end
   $var wire 1 * en $end
   $var wire 1 /! clr $end
   $var wire 32 ,! d [31:0] $end
   $var wire 32 + q [31:0] $end
  $upscope $end
  $scope module PCmux $end
   $var wire 32 .! WIDTH [31:0] $end
   $var wire 32 , d0 [31:0] $end
   $var wire 32 & d1 [31:0] $end
   $var wire 1 % s $end
   $var wire 32 ,! y [31:0] $end
  $upscope $end
  $scope module PCplus4 $end
   $var wire 32 .! WIDTH [31:0] $end
   $var wire 32 + a [31:0] $end
   $var wire 32 0! b [31:0] $end
   $var wire 1 /! cin $end
   $var wire 32 , sum [31:0] $end
   $var wire 1 - cout $end
   $var wire 32 . carry [31:0] $end
   $scope module a1 $end
    $var wire 1 / a $end
    $var wire 1 /! b $end
    $var wire 1 /! cin $end
    $var wire 1 / sum $end
    $var wire 1 /! cout $end
   $upscope $end
   $scope module a10 $end
    $var wire 1 0 a $end
    $var wire 1 /! b $end
    $var wire 1 1 cin $end
    $var wire 1 2 sum $end
    $var wire 1 3 cout $end
   $upscope $end
   $scope module a11 $end
    $var wire 1 4 a $end
    $var wire 1 /! b $end
    $var wire 1 3 cin $end
    $var wire 1 5 sum $end
    $var wire 1 6 cout $end
   $upscope $end
   $scope module a12 $end
    $var wire 1 7 a $end
    $var wire 1 /! b $end
    $var wire 1 6 cin $end
    $var wire 1 8 sum $end
    $var wire 1 9 cout $end
   $upscope $end
   $scope module a13 $end
    $var wire 1 : a $end
    $var wire 1 /! b $end
    $var wire 1 9 cin $end
    $var wire 1 ; sum $end
    $var wire 1 < cout $end
   $upscope $end
   $scope module a14 $end
    $var wire 1 = a $end
    $var wire 1 /! b $end
    $var wire 1 < cin $end
    $var wire 1 > sum $end
    $var wire 1 ? cout $end
   $upscope $end
   $scope module a15 $end
    $var wire 1 @ a $end
    $var wire 1 /! b $end
    $var wire 1 ? cin $end
    $var wire 1 A sum $end
    $var wire 1 B cout $end
   $upscope $end
   $scope module a16 $end
    $var wire 1 C a $end
    $var wire 1 /! b $end
    $var wire 1 B cin $end
    $var wire 1 D sum $end
    $var wire 1 E cout $end
   $upscope $end
   $scope module a17 $end
    $var wire 1 F a $end
    $var wire 1 /! b $end
    $var wire 1 E cin $end
    $var wire 1 G sum $end
    $var wire 1 H cout $end
   $upscope $end
   $scope module a18 $end
    $var wire 1 I a $end
    $var wire 1 /! b $end
    $var wire 1 H cin $end
    $var wire 1 J sum $end
    $var wire 1 K cout $end
   $upscope $end
   $scope module a19 $end
    $var wire 1 L a $end
    $var wire 1 /! b $end
    $var wire 1 K cin $end
    $var wire 1 M sum $end
    $var wire 1 N cout $end
   $upscope $end
   $scope module a2 $end
    $var wire 1 O a $end
    $var wire 1 /! b $end
    $var wire 1 /! cin $end
    $var wire 1 O sum $end
    $var wire 1 /! cout $end
   $upscope $end
   $scope module a20 $end
    $var wire 1 P a $end
    $var wire 1 /! b $end
    $var wire 1 N cin $end
    $var wire 1 Q sum $end
    $var wire 1 R cout $end
   $upscope $end
   $scope module a21 $end
    $var wire 1 S a $end
    $var wire 1 /! b $end
    $var wire 1 R cin $end
    $var wire 1 T sum $end
    $var wire 1 U cout $end
   $upscope $end
   $scope module a22 $end
    $var wire 1 V a $end
    $var wire 1 /! b $end
    $var wire 1 U cin $end
    $var wire 1 W sum $end
    $var wire 1 X cout $end
   $upscope $end
   $scope module a23 $end
    $var wire 1 Y a $end
    $var wire 1 /! b $end
    $var wire 1 X cin $end
    $var wire 1 Z sum $end
    $var wire 1 [ cout $end
   $upscope $end
   $scope module a24 $end
    $var wire 1 \ a $end
    $var wire 1 /! b $end
    $var wire 1 [ cin $end
    $var wire 1 ] sum $end
    $var wire 1 ^ cout $end
   $upscope $end
   $scope module a25 $end
    $var wire 1 _ a $end
    $var wire 1 /! b $end
    $var wire 1 ^ cin $end
    $var wire 1 ` sum $end
    $var wire 1 a cout $end
   $upscope $end
   $scope module a26 $end
    $var wire 1 b a $end
    $var wire 1 /! b $end
    $var wire 1 a cin $end
    $var wire 1 c sum $end
    $var wire 1 d cout $end
   $upscope $end
   $scope module a27 $end
    $var wire 1 e a $end
    $var wire 1 /! b $end
    $var wire 1 d cin $end
    $var wire 1 f sum $end
    $var wire 1 g cout $end
   $upscope $end
   $scope module a28 $end
    $var wire 1 h a $end
    $var wire 1 /! b $end
    $var wire 1 g cin $end
    $var wire 1 i sum $end
    $var wire 1 j cout $end
   $upscope $end
   $scope module a29 $end
    $var wire 1 k a $end
    $var wire 1 /! b $end
    $var wire 1 j cin $end
    $var wire 1 l sum $end
    $var wire 1 m cout $end
   $upscope $end
   $scope module a3 $end
    $var wire 1 n a $end
    $var wire 1 1! b $end
    $var wire 1 /! cin $end
    $var wire 1 o sum $end
    $var wire 1 n cout $end
   $upscope $end
   $scope module a30 $end
    $var wire 1 p a $end
    $var wire 1 /! b $end
    $var wire 1 m cin $end
    $var wire 1 q sum $end
    $var wire 1 r cout $end
   $upscope $end
   $scope module a31 $end
    $var wire 1 s a $end
    $var wire 1 /! b $end
    $var wire 1 r cin $end
    $var wire 1 t sum $end
    $var wire 1 u cout $end
   $upscope $end
   $scope module a32 $end
    $var wire 1 v a $end
    $var wire 1 /! b $end
    $var wire 1 u cin $end
    $var wire 1 w sum $end
    $var wire 1 - cout $end
   $upscope $end
   $scope module a4 $end
    $var wire 1 x a $end
    $var wire 1 /! b $end
    $var wire 1 n cin $end
    $var wire 1 y sum $end
    $var wire 1 z cout $end
   $upscope $end
   $scope module a5 $end
    $var wire 1 { a $end
    $var wire 1 /! b $end
    $var wire 1 z cin $end
    $var wire 1 | sum $end
    $var wire 1 } cout $end
   $upscope $end
   $scope module a6 $end
    $var wire 1 ~ a $end
    $var wire 1 /! b $end
    $var wire 1 } cin $end
    $var wire 1 !! sum $end
    $var wire 1 "! cout $end
   $upscope $end
   $scope module a7 $end
    $var wire 1 #! a $end
    $var wire 1 /! b $end
    $var wire 1 "! cin $end
    $var wire 1 $! sum $end
    $var wire 1 %! cout $end
   $upscope $end
   $scope module a8 $end
    $var wire 1 &! a $end
    $var wire 1 /! b $end
    $var wire 1 %! cin $end
    $var wire 1 '! sum $end
    $var wire 1 (! cout $end
   $upscope $end
   $scope module a9 $end
    $var wire 1 )! a $end
    $var wire 1 /! b $end
    $var wire 1 (! cin $end
    $var wire 1 *! sum $end
    $var wire 1 1 cout $end
   $upscope $end
  $upscope $end
  $scope module imem $end
   $var wire 32 + a [31:0] $end
   $var wire 32 -! rd [31:0] $end
  $upscope $end
 $upscope $end
$enddefinitions $end


#0
1#
0$
0%
b00000000000000000000000000000000 &
b00000000000000000000000000000000 '
b00000000000000000000000000000000 (
b00000000000000000000000000000000 )
1*
b00000000000000000000000000000000 +
b00000000000000000000000000000100 ,
0-
b00000000000000000000000000000000 .
0/
00
01
02
03
04
05
06
07
08
09
0:
0;
0<
0=
0>
0?
0@
0A
0B
0C
0D
0E
0F
0G
0H
0I
0J
0K
0L
0M
0N
0O
0P
0Q
0R
0S
0T
0U
0V
0W
0X
0Y
0Z
0[
0\
0]
0^
0_
0`
0a
0b
0c
0d
0e
0f
0g
0h
0i
0j
0k
0l
0m
0n
1o
0p
0q
0r
0s
0t
0u
0v
0w
0x
0y
0z
0{
0|
0}
0~
0!!
0"!
0#!
0$!
0%!
0&!
0'!
0(!
0)!
0*!
1+!
b00000000000000000000000000000100 ,!
b00000000010100000000000100010011 -!
b00000000000000000000000000100000 .!
0/!
b00000000000000000000000000000100 0!
11!
#5000
0+!
#10000
b00000000000000000000000000000001 '
1+!
#11000
1%
b00000000000000000000000000100000 &
b00000000000000000000000000000001 (
b00000000000000000000000000100000 ,!
#15000
0+!
#20000
b00000000000000000000000000000010 '
1+!
#21000
1$
0%
b00000000000000000000000000000000 &
b00000000000000000000000000000010 (
0*
b00000000000000000000000000000100 ,!
#25000
0+!
#30000
b00000000000000000000000000000011 '
1+!
#31000
0#
0$
b00000000000000000000000000000011 (
1*
#35000
0+!
#40000
b00000000000000000000000000000100 '
b00000000000000000000000000000100 +
b00000000000000000000000000001000 ,
b00000000000000000000000000000100 .
1n
0o
1y
1+!
b00000000000000000000000000001000 ,!
b00000000110000000000000110010011 -!
#41000
b00000000000000000000000000000100 (
#45000
0+!
#50000
b00000000000000000000000000000101 '
b00000000000000000000000000001000 +
b00000000000000000000000000001100 ,
b00000000000000000000000000000000 .
0n
1o
1x
1+!
b00000000000000000000000000001100 ,!
b11111111011100011000001110010011 -!
#51000
b00000000000000000000000000000101 (
#55000
0+!
#60000
b00000000000000000000000000000110 '
b00000000000000000000000000001100 +
b00000000000000000000000000010000 ,
b00000000000000000000000000001100 .
1n
0o
0y
1z
1|
1+!
b00000000000000000000000000010000 ,!
b00000000001000111110001000110011 -!
#61000
b00000000000000000000000000000110 (
#65000
0+!
#70000
b00000000000000000000000000000111 '
b00000000000000000000000000010000 +
b00000000000000000000000000010100 ,
b00000000000000000000000000000000 .
0n
1o
0x
0z
1{
1+!
b00000000000000000000000000010100 ,!
b00000000010000011111001010110011 -!
#71000
1%
b00000000000000000000000000000111 (
b00000000000000000000000000000000 ,!
#72000
0%
b00000000000000000000000000010100 ,!
#75000
0+!
#80000
b00000000000000000000000000001000 '
b00000000000000000000000000010100 +
b00000000000000000000000000011000 ,
b00000000000000000000000000000100 .
1n
0o
1y
1+!
b00000000000000000000000000011000 ,!
b00000000010000101000001010110011 -!
#81000
1$
b00000000000000000000000000001000 (
0*
#85000
0+!
#90000
b00000000000000000000000000001001 '
1+!
#91000
b00000000000000000000000000001001 (
#95000
0+!
#100000
b00000000000000000000000000001010 '
1+!
#101000
b00000000000000000000000000001010 (
#105000
0+!
#110000
b00000000000000000000000000001011 '
1+!
#111000
b00000000000000000000000000001011 (
#115000
0+!
#120000
b00000000000000000000000000001100 '
1+!
#121000
1%
b00000000000000000000000000100000 &
b00000000000000000000000000001100 (
b00000000000000000000000000100000 ,!
#125000
0+!
#130000
b00000000000000000000000000001101 '
1+!
#131000
0$
b00000000000000000000000000001101 (
1*
#135000
0+!
#140000
b00000000000000000000000000001110 '
b00000000000000000000000000100000 +
b00000000000000000000000000100100 ,
b00000000000000000000000000000000 .
0n
1o
0y
0{
0|
1~
1!!
1+!
b00000000000000100000010001100011 -!
#141000
b00000000000000000000000000001000 &
b00000000000000000000000000001110 (
b00000000000000000000000000001000 ,!
#145000
0+!
#150000
b00000000000000000000000000001111 '
b00000000000000000000000000001000 +
b00000000000000000000000000001100 ,
1x
1y
0~
0!!
1+!
b11111111011100011000001110010011 -!
#151000
b00000000000000000000000000010000 &
b00000000000000000000000000001111 (
b00000000000000000000000000010000 ,!
#155000
0+!
#160000
b00000000000000000000000000010000 '
b00000000000000000000000000010000 +
b00000000000000000000000000010100 ,
0x
0y
1{
1|
1+!
b00000000010000011111001010110011 -!
#161000
b00000000000000000000000000010000 (
#165000
0+!
#170000
b00000000000000000000000000010001 '
1+!
#171000
b11111111111111111111111111111100 &
b00000000000000000000000000010001 (
b11111111111111111111111111111100 ,!
#175000
0+!
#180000
b00000000000000000000000000010010 '
b11111111111111111111111111111100 +
b00000000000000000000000000000000 ,
1-
b11111111111111111111111111111100 .
10
11
13
14
16
17
19
1:
1<
1=
1?
1@
1B
1C
1E
1F
1H
1I
1K
1L
1N
1P
1R
1S
1U
1V
1X
1Y
1[
1\
1^
1_
1a
1b
1d
1e
1g
1h
1j
1k
1m
1n
0o
1p
1r
1s
1u
1v
1x
1z
0|
1}
1~
1"!
1#!
1%!
1&!
1(!
1)!
1+!
b00000000000000000000000000000000 -!
#181000
0%
b00000000000000000000000000010010 (
b00000000000000000000000000000000 ,!
#185000
0+!
#190000
b00000000000000000000000000010011 '
b00000000000000000000000000000000 +
b00000000000000000000000000000100 ,
0-
b00000000000000000000000000000000 .
00
01
03
04
06
07
09
0:
0<
0=
0?
0@
0B
0C
0E
0F
0H
0I
0K
0L
0N
0P
0R
0S
0U
0V
0X
0Y
0[
0\
0^
0_
0a
0b
0d
0e
0g
0h
0j
0k
0m
0n
1o
0p
0r
0s
0u
0v
0x
0z
0{
0}
0~
0"!
0#!
0%!
0&!
0(!
0)!
1+!
b00000000000000000000000000000100 ,!
b00000000010100000000000100010011 -!
#191000
1%
b00000000000000000000000000100000 &
b00000000000000000000000000010011 (
b00000000000000000000000000100000 ,!
#192000
0%
b00000000000000000000000000000100 ,!
#193000
1$
0*
#194000
1#
#195000
0+!
#200000
b00000000000000000000000000010100 '
1+!
#201000
b00000000000000000000000000010100 (
